[{"app_name":"Kitchen.Sink.Lights","client":"172.17.0.1:46860","collector.name":"ktranslate","device_name":"HubitatC8Pro","facility":1,"hostname":"HubitatC8Pro","instrumentation.name":"ktranslate-syslog","instrumentation.provider":"kentik","message":"Kitchen Sink Lights on HubitatC8Pro-2 was turned on [digital]","messageId":"7d95f192-3c1c-41f1-85cd-18a902125595","msg_id":"-","newrelic.logs.batchIndex":25,"newrelic.source":"api.logs","plugin.type":"ktranslate-syslog","priority":14,"proc_id":"4390","severity":6,"structured_data":"-","tags.container_service":"syslog","timestamp":1761252618280,"version":1},{"app_name":"Kitchen.Sink.Lights","client":"172.17.0.1:46860","collector.name":"ktranslate","device_name":"HubitatC8Pro","facility":1,"hostname":"HubitatC8Pro","instrumentation.name":"ktranslate-syslog","instrumentation.provider":"kentik","message":"Kitchen Sink Lights on HubitatC8Pro-2 was set to 99% [digital]","messageId":"d1803334-a9b6-4c92-bee8-4ae611cc6985","msg_id":"-","newrelic.logs.batchIndex":31,"newrelic.source":"api.logs","plugin.type":"ktranslate-syslog","priority":14,"proc_id":"4390","severity":6,"structured_data":"-","tags.container_service":"syslog","timestamp":1761252618564,"version":1},{"app_name":"Light.Monitor.Wrapper","client":"172.17.0.1:46860","collector.name":"ktranslate","device_name":"HubitatC8Pro-2","facility":1,"hostname":"HubitatC8Pro-2","instrumentation.name":"ktranslate-syslog","instrumentation.provider":"kentik","message":"Light Monitor App: Devices currently in monitoringState: Front Door Light (ID: 1920), Kitchen Sink Lights (ID: 2997), Pool Light (ID: 1870), Garage Inside Light (ID: 855), Kitchen Desk Light (ID: 977), Patio Lights (ID: 968), Kitchen Counter Light Left (ID: 957), Patio Door and Back Deck Steps Lights (ID: 969), Garage Side Outside Light (ID: 1380)","messageId":"bc0c2bc4-b229-4164-b406-01221c7c70ef","msg_id":"-","newrelic.logs.batchIndex":57,"newrelic.source":"api.logs","plugin.type":"ktranslate-syslog","priority":15,"proc_id":"1588","severity":7,"structured_data":"-","tags.container_service":"syslog","timestamp":1761252618779,"version":1},{"app_name":"Kitchen.Sink.Lights","client":"172.17.0.1:46860","collector.name":"ktranslate","device_name":"HubitatC8Pro","facility":1,"hostname":"HubitatC8Pro","instrumentation.name":"ktranslate-syslog","instrumentation.provider":"kentik","message":"Kitchen Sink Lights on HubitatC8Pro-2 was turned on [physical]","messageId":"a63657a7-ba6d-472a-9e9c-7c1027616dfd","msg_id":"-","newrelic.logs.batchIndex":44,"newrelic.source":"api.logs","plugin.type":"ktranslate-syslog","priority":14,"proc_id":"4390","severity":6,"structured_data":"-","tags.container_service":"syslog","timestamp":1761252618861,"version":1},{"app_name":"Kitchen.Sink.Lights","client":"172.17.0.1:46860","collector.name":"ktranslate","device_name":"HubitatC8Pro","facility":1,"hostname":"HubitatC8Pro","instrumentation.name":"ktranslate-syslog","instrumentation.provider":"kentik","message":"Kitchen Sink Lights on HubitatC8Pro-2 was set to 99% [physical]","messageId":"963a1212-6d54-4dab-89bd-f16f3d02b8d8","msg_id":"-","newrelic.logs.batchIndex":49,"newrelic.source":"api.logs","plugin.type":"ktranslate-syslog","priority":14,"proc_id":"4390","severity":6,"structured_data":"-","tags.container_service":"syslog","timestamp":1761252618864,"version":1},{"app_name":"Kitchen.Sink.Lights","client":"172.17.0.1:46860","collector.name":"ktranslate","device_name":"HubitatC8Pro-2","facility":1,"hostname":"HubitatC8Pro-2","instrumentation.name":"ktranslate-syslog","instrumentation.provider":"kentik","message":"Kitchen Sink Lights was turned on [digital]","messageId":"63a05175-256d-489f-96a8-71afa9d4f33f","msg_id":"-","newrelic.logs.batchIndex":2,"newrelic.source":"api.logs","plugin.type":"ktranslate-syslog","priority":14,"proc_id":"2997","severity":6,"structured_data":"-","tags.container_service":"syslog","timestamp":1761252619060,"version":1},{"app_name":"Light.Monitor.Wrapper","client":"172.17.0.1:46860","collector.name":"ktranslate","device_name":"HubitatC8Pro-2","facility":1,"hostname":"HubitatC8Pro-2","instrumentation.name":"ktranslate-syslog","instrumentation.provider":"kentik","message":"Light Monitor App: Devices currently in monitoringState: Front Door Light (ID: 1920), Kitchen Sink Lights (ID: 2997), Pool Light (ID: 1870), Garage Inside Light (ID: 855), Kitchen Desk Light (ID: 977), Patio Lights (ID: 968), Kitchen Counter Light Left (ID: 957), Patio Door and Back Deck Steps Lights (ID: 969), Garage Side Outside Light (ID: 1380)","messageId":"4fe6447e-9d08-4e43-8237-d2871ff8f257","msg_id":"-","newrelic.logs.batchIndex":4,"newrelic.source":"api.logs","plugin.type":"ktranslate-syslog","priority":15,"proc_id":"1588","severity":7,"structured_data":"-","tags.container_service":"syslog","timestamp":1761252619222,"version":1},{"app_name":"Kitchen.Sink.Lights","client":"172.17.0.1:46860","collector.name":"ktranslate","device_name":"HubitatC8Pro-2","facility":1,"hostname":"HubitatC8Pro-2","instrumentation.name":"ktranslate-syslog","instrumentation.provider":"kentik","message":"Kitchen Sink Lights was set to 99% [digital]","messageId":"4c2401af-4a45-4363-83f0-4427183dc1a0","msg_id":"-","newrelic.logs.batchIndex":12,"newrelic.source":"api.logs","plugin.type":"ktranslate-syslog","priority":14,"proc_id":"2997","severity":6,"structured_data":"-","tags.container_service":"syslog","timestamp":1761252619225,"version":1},{"app_name":"Kitchen.Sink.Lights","client":"172.17.0.1:46860","collector.name":"ktranslate","device_name":"HubitatC8Pro-2","facility":1,"hostname":"HubitatC8Pro-2","instrumentation.name":"ktranslate-syslog","instrumentation.provider":"kentik","message":"Kitchen Sink Lights was turned on [physical]","messageId":"abe433b2-2bdf-42f2-b5bd-4e4a10c109d5","msg_id":"-","newrelic.logs.batchIndex":45,"newrelic.source":"api.logs","plugin.type":"ktranslate-syslog","priority":14,"proc_id":"2997","severity":6,"structured_data":"-","tags.container_service":"syslog","timestamp":1761252619700,"version":1},{"app_name":"Kitchen.Sink.Lights","client":"172.17.0.1:46860","collector.name":"ktranslate","device_name":"HubitatC8Pro-2","facility":1,"hostname":"HubitatC8Pro-2","instrumentation.name":"ktranslate-syslog","instrumentation.provider":"kentik","message":"Kitchen Sink Lights was set to 99% [physical]","messageId":"4b1b1422-4a0e-4dfa-ac76-51d304d2150d","msg_id":"-","newrelic.logs.batchIndex":46,"newrelic.source":"api.logs","plugin.type":"ktranslate-syslog","priority":14,"proc_id":"2997","severity":6,"structured_data":"-","tags.container_service":"syslog","timestamp":1761252619706,"version":1},{"app_name":"Light.Monitor.Wrapper","client":"172.17.0.1:46860","collector.name":"ktranslate","device_name":"HubitatC8Pro-2","facility":1,"hostname":"HubitatC8Pro-2","instrumentation.name":"ktranslate-syslog","instrumentation.provider":"kentik","message":"Light Monitor App: Devices currently in monitoringState: Front Door Light (ID: 1920), Kitchen Sink Lights (ID: 2997), Pool Light (ID: 1870), Garage Inside Light (ID: 855), Kitchen Desk Light (ID: 977), Patio Lights (ID: 968), Kitchen Counter Light Left (ID: 957), Patio Door and Back Deck Steps Lights (ID: 969), Garage Side Outside Light (ID: 1380)","messageId":"eb75ace4-b246-49d8-8baa-5757267bd031","msg_id":"-","newrelic.logs.batchIndex":47,"newrelic.source":"api.logs","plugin.type":"ktranslate-syslog","priority":15,"proc_id":"1588","severity":7,"structured_data":"-","tags.container_service":"syslog","timestamp":1761252619707,"version":1},{"app_name":"Light.Monitor.Wrapper","client":"172.17.0.1:46860","collector.name":"ktranslate","device_name":"HubitatC8Pro-2","facility":1,"hostname":"HubitatC8Pro-2","instrumentation.name":"ktranslate-syslog","instrumentation.provider":"kentik","message":"Light Monitor App: Devices currently in monitoringState: Front Door Light (ID: 1920), Kitchen Sink Lights (ID: 2997), Pool Light (ID: 1870), Garage Inside Light (ID: 855), Kitchen Desk Light (ID: 977), Patio Lights (ID: 968), Kitchen Counter Light Left (ID: 957), Patio Door and Back Deck Steps Lights (ID: 969), Garage Side Outside Light (ID: 1380)","messageId":"2d442c84-f6c6-435e-9ebd-d485cba2a7dd","msg_id":"-","newrelic.logs.batchIndex":49,"newrelic.source":"api.logs","plugin.type":"ktranslate-syslog","priority":15,"proc_id":"1588","severity":7,"structured_data":"-","tags.container_service":"syslog","timestamp":1761252619710,"version":1},{"app_name":"Light.Monitor.Wrapper","client":"172.17.0.1:46860","collector.name":"ktranslate","device_name":"HubitatC8Pro-2","facility":1,"hostname":"HubitatC8Pro-2","instrumentation.name":"ktranslate-syslog","instrumentation.provider":"kentik","message":"Light Monitor App: Checking for stuck monitoring state for Kitchen Sink Lights:","messageId":"ea0e63b5-7a8c-40cf-b072-ca3d421dfd9f","msg_id":"-","newrelic.logs.batchIndex":50,"newrelic.source":"api.logs","plugin.type":"ktranslate-syslog","priority":15,"proc_id":"1588","severity":7,"structured_data":"-","tags.container_service":"syslog","timestamp":1761252619711,"version":1},{"app_name":"Light.Monitor.Wrapper","client":"172.17.0.1:46860","collector.name":"ktranslate","device_name":"HubitatC8Pro-2","facility":1,"hostname":"HubitatC8Pro-2","instrumentation.name":"ktranslate-syslog","instrumentation.provider":"kentik","message":"Light Monitor App:   - Desired state: off, Current monitoring state: [desiredState:off, lastCheck:1761245537744, initialState:off, refreshCount:0, lastCommand:off, externalEvent:true, checkCount:0, startTime:1761245537744, deviceName:Kitchen Sink Lights, waitingForRefresh:false, refreshSent:false]","messageId":"2eadab85-eb1b-456d-af32-5300784282b4","msg_id":"-","newrelic.logs.batchIndex":67,"newrelic.source":"api.logs","plugin.type":"ktranslate-syslog","priority":15,"proc_id":"1588","severity":7,"structured_data":"-","tags.container_service":"syslog","timestamp":1761252619784,"version":1},{"app_name":"Light.Monitor.Wrapper","client":"172.17.0.1:46860","collector.name":"ktranslate","device_name":"HubitatC8Pro-2","facility":1,"hostname":"HubitatC8Pro-2","instrumentation.name":"ktranslate-syslog","instrumentation.provider":"kentik","message":"Light Monitor App: Device Kitchen Sink Lights (ID: 2997) was stuck in monitoringState - clearing before starting new monitoring cycle","messageId":"d0608711-45c6-4a4c-ac2f-d3328e64ad21","msg_id":"-","newrelic.logs.batchIndex":70,"newrelic.source":"api.logs","plugin.type":"ktranslate-syslog","priority":12,"proc_id":"1588","severity":4,"structured_data":"-","tags.container_service":"syslog","timestamp":1761252619794,"version":1},{"app_name":"Light.Monitor.Wrapper","client":"172.17.0.1:46860","collector.name":"ktranslate","device_name":"HubitatC8Pro-2","facility":1,"hostname":"HubitatC8Pro-2","instrumentation.name":"ktranslate-syslog","instrumentation.provider":"kentik","message":"Light Monitor App: EVENT RECEIVED - Device: Kitchen Sink Lights, State: on, Source: DEVICE, Type: digital, Description: null, Event: Event[archivable=true,data=<null>,dataString=<null>,date=Thu Oct 23 15:50:19 EDT 2025,description=<null>,descriptionText=Kitchen Sink Lights was turned on [digital],device=<null>,deviceId=2997,displayName=Kitchen Sink Lights,displayed=true,forceAttributeUpdate=false,hubId=<null>,id=52478672,installedAppId=<null>,isStateChange=true,location=<null>,locationId=<null>,name=switch,producedBy=<null>,source=DEVICE,subscriptionData=<null>,translatable=false,triggeredListeners=<null>,type=digital,unit=<null>,value=on]","messageId":"98c22b36-d2b5-4fce-b8fe-74916c04255d","msg_id":"-","newrelic.logs.batchIndex":82,"newrelic.source":"api.logs","plugin.type":"ktranslate-syslog","priority":15,"proc_id":"1588","severity":7,"structured_data":"-","tags.container_service":"syslog","timestamp":1761252619813,"version":1},{"app_name":"Light.Monitor.Wrapper","client":"172.17.0.1:46860","collector.name":"ktranslate","device_name":"HubitatC8Pro-2","facility":1,"hostname":"HubitatC8Pro-2","instrumentation.name":"ktranslate-syslog","instrumentation.provider":"kentik","message":"Light Monitor App: Last command time for device Kitchen Sink Lights: 1761236788980 (2025-10-23 12:26:28)","messageId":"b09e271d-7f13-4ba3-adee-51b0ab7ea509","msg_id":"-","newrelic.logs.batchIndex":83,"newrelic.source":"api.logs","plugin.type":"ktranslate-syslog","priority":15,"proc_id":"1588","severity":7,"structured_data":"-","tags.container_service":"syslog","timestamp":1761252619815,"version":1},{"app_name":"Light.Monitor.Wrapper","client":"172.17.0.1:46860","collector.name":"ktranslate","device_name":"HubitatC8Pro-2","facility":1,"hostname":"HubitatC8Pro-2","instrumentation.name":"ktranslate-syslog","instrumentation.provider":"kentik","message":"Light Monitor App: Time since last command for device Kitchen Sink Lights: 12230.553s","messageId":"9e8e5b50-266e-4527-ba79-7d7c48d48318","msg_id":"-","newrelic.logs.batchIndex":84,"newrelic.source":"api.logs","plugin.type":"ktranslate-syslog","priority":15,"proc_id":"1588","severity":7,"structured_data":"-","tags.container_service":"syslog","timestamp":1761252619817,"version":1},{"app_name":"Light.Monitor.Wrapper","client":"172.17.0.1:46860","collector.name":"ktranslate","device_name":"HubitatC8Pro-2","facility":1,"hostname":"HubitatC8Pro-2","instrumentation.name":"ktranslate-syslog","instrumentation.provider":"kentik","message":"Light Monitor App: Device type for Kitchen Sink Lights: Generic Z-Wave Dimmer","messageId":"12351fe6-8c1c-4c84-9f1f-72f639f5dc78","msg_id":"-","newrelic.logs.batchIndex":86,"newrelic.source":"api.logs","plugin.type":"ktranslate-syslog","priority":15,"proc_id":"1588","severity":7,"structured_data":"-","tags.container_service":"syslog","timestamp":1761252619819,"version":1},{"app_name":"Light.Monitor.Wrapper","client":"172.17.0.1:46860","collector.name":"ktranslate","device_name":"HubitatC8Pro-2","facility":1,"hostname":"HubitatC8Pro-2","instrumentation.name":"ktranslate-syslog","instrumentation.provider":"kentik","message":"Light Monitor App: MONITORING STARTED - Light Kitchen Sink Lights (ID: 2997) changing to on at 2025-10-23 15:50:19","messageId":"62f74e00-4ce7-4a51-b84a-486bc355df12","msg_id":"-","newrelic.logs.batchIndex":87,"newrelic.source":"api.logs","plugin.type":"ktranslate-syslog","priority":14,"proc_id":"1588","severity":6,"structured_data":"-","tags.container_service":"syslog","timestamp":1761252619821,"version":1},{"app_name":"Light.Monitor.Wrapper","client":"172.17.0.1:46860","collector.name":"ktranslate","device_name":"HubitatC8Pro-2","facility":1,"hostname":"HubitatC8Pro-2","instrumentation.name":"ktranslate-syslog","instrumentation.provider":"kentik","message":"Light Monitor App: Adding device Kitchen Sink Lights (ID: 2997) to monitoringState.","messageId":"ab922ead-ba04-4549-bb70-39c6e0a21a12","msg_id":"-","newrelic.logs.batchIndex":88,"newrelic.source":"api.logs","plugin.type":"ktranslate-syslog","priority":15,"proc_id":"1588","severity":7,"structured_data":"-","tags.container_service":"syslog","timestamp":1761252619823,"version":1},{"app_name":"Light.Monitor.Wrapper","client":"172.17.0.1:46860","collector.name":"ktranslate","device_name":"HubitatC8Pro-2","facility":1,"hostname":"HubitatC8Pro-2","instrumentation.name":"ktranslate-syslog","instrumentation.provider":"kentik","message":"Light Monitor App: Device event details - ID: 2997, Name: Kitchen Sink Lights, New State: on, Event Source: DEVICE","messageId":"1338e3db-78ce-4925-aab3-4483e0966a0e","msg_id":"-","newrelic.logs.batchIndex":89,"newrelic.source":"api.logs","plugin.type":"ktranslate-syslog","priority":15,"proc_id":"1588","severity":7,"structured_data":"-","tags.container_service":"syslog","timestamp":1761252619825,"version":1},{"app_name":"Light.Monitor.Wrapper","client":"172.17.0.1:46860","collector.name":"ktranslate","device_name":"HubitatC8Pro-2","facility":1,"hostname":"HubitatC8Pro-2","instrumentation.name":"ktranslate-syslog","instrumentation.provider":"kentik","message":"Light Monitor App: Scheduling initial check for device Kitchen Sink Lights in 30 seconds","messageId":"228b56ac-ad5d-442b-ad22-7c138a6cb973","msg_id":"-","newrelic.logs.batchIndex":99,"newrelic.source":"api.logs","plugin.type":"ktranslate-syslog","priority":15,"proc_id":"1588","severity":7,"structured_data":"-","tags.container_service":"syslog","timestamp":1761252619959,"version":1},{"app_name":"Light.Monitor.Wrapper","client":"172.17.0.1:46860","collector.name":"ktranslate","device_name":"HubitatC8Pro-2","facility":1,"hostname":"HubitatC8Pro-2","instrumentation.name":"ktranslate-syslog","instrumentation.provider":"kentik","message":"Light Monitor App: Setting up timeout check for device Kitchen Sink Lights in 600 seconds","messageId":"41c0e63e-e3e7-4c5b-8869-968d8c940730","msg_id":"-","newrelic.logs.batchIndex":125,"newrelic.source":"api.logs","plugin.type":"ktranslate-syslog","priority":15,"proc_id":"1588","severity":7,"structured_data":"-","tags.container_service":"syslog","timestamp":1761252620198,"version":1},{"app_name":"Kitchen.Sink.Lights","client":"172.17.0.1:46860","collector.name":"ktranslate","device_name":"HubitatC8Pro","facility":1,"hostname":"HubitatC8Pro","instrumentation.name":"ktranslate-syslog","instrumentation.provider":"kentik","message":"Kitchen Sink Lights on HubitatC8Pro-2 is on [digital]","messageId":"927da932-4398-4709-8934-666b9b2a5178","msg_id":"-","newrelic.logs.batchIndex":3,"newrelic.source":"api.logs","plugin.type":"ktranslate-syslog","priority":14,"proc_id":"4390","severity":6,"structured_data":"-","tags.container_service":"syslog","timestamp":1761252622913,"version":1},{"app_name":"Kitchen.Sink.Lights","client":"172.17.0.1:46860","collector.name":"ktranslate","device_name":"HubitatC8Pro","facility":1,"hostname":"HubitatC8Pro","instrumentation.name":"ktranslate-syslog","instrumentation.provider":"kentik","message":"Kitchen Sink Lights on HubitatC8Pro-2 is at 99% [digital]","messageId":"1e15dfc3-a501-4c81-98fe-b278f14d095b","msg_id":"-","newrelic.logs.batchIndex":4,"newrelic.source":"api.logs","plugin.type":"ktranslate-syslog","priority":14,"proc_id":"4390","severity":6,"structured_data":"-","tags.container_service":"syslog","timestamp":1761252622916,"version":1},{"app_name":"Kitchen.Sink.Lights","client":"172.17.0.1:46860","collector.name":"ktranslate","device_name":"HubitatC8Pro-2","facility":1,"hostname":"HubitatC8Pro-2","instrumentation.name":"ktranslate-syslog","instrumentation.provider":"kentik","message":"Kitchen Sink Lights is on [digital]","messageId":"215dd104-699f-4613-a564-b7bfd3776337","msg_id":"-","newrelic.logs.batchIndex":1,"newrelic.source":"api.logs","plugin.type":"ktranslate-syslog","priority":14,"proc_id":"2997","severity":6,"structured_data":"-","tags.container_service":"syslog","timestamp":1761252623872,"version":1},{"app_name":"Kitchen.Sink.Lights","client":"172.17.0.1:46860","collector.name":"ktranslate","device_name":"HubitatC8Pro-2","facility":1,"hostname":"HubitatC8Pro-2","instrumentation.name":"ktranslate-syslog","instrumentation.provider":"kentik","message":"Kitchen Sink Lights is at 99% [digital]","messageId":"8b42a54e-8a19-4476-979c-92ac0be35440","msg_id":"-","newrelic.logs.batchIndex":2,"newrelic.source":"api.logs","plugin.type":"ktranslate-syslog","priority":14,"proc_id":"2997","severity":6,"structured_data":"-","tags.container_service":"syslog","timestamp":1761252623873,"version":1},{"app_name":"Kitchen.Sink.Lights","client":"172.17.0.1:46860","collector.name":"ktranslate","device_name":"HubitatC8Pro","facility":1,"hostname":"HubitatC8Pro","instrumentation.name":"ktranslate-syslog","instrumentation.provider":"kentik","message":"Kitchen Sink Lights on HubitatC8Pro-2 is on [digital]","messageId":"97dfe87d-ed8b-4c17-982a-929ab8392036","msg_id":"-","newrelic.logs.batchIndex":3,"newrelic.source":"api.logs","plugin.type":"ktranslate-syslog","priority":14,"proc_id":"4390","severity":6,"structured_data":"-","tags.container_service":"syslog","timestamp":1761252649408,"version":1},{"app_name":"Kitchen.Sink.Lights","client":"172.17.0.1:46860","collector.name":"ktranslate","device_name":"HubitatC8Pro","facility":1,"hostname":"HubitatC8Pro","instrumentation.name":"ktranslate-syslog","instrumentation.provider":"kentik","message":"Kitchen Sink Lights on HubitatC8Pro-2 is at 99% [digital]","messageId":"761d7de5-9df8-46d4-a0fa-3101362ae606","msg_id":"-","newrelic.logs.batchIndex":4,"newrelic.source":"api.logs","plugin.type":"ktranslate-syslog","priority":14,"proc_id":"4390","severity":6,"structured_data":"-","tags.container_service":"syslog","timestamp":1761252649411,"version":1},{"app_name":"Light.Monitor.Wrapper","client":"172.17.0.1:46860","collector.name":"ktranslate","device_name":"HubitatC8Pro-2","facility":1,"hostname":"HubitatC8Pro-2","instrumentation.name":"ktranslate-syslog","instrumentation.provider":"kentik","message":"Light Monitor App: Sending REFRESH command to device Kitchen Sink Lights to get accurate state","messageId":"349a290f-3b27-4266-8934-86e8a4b83160","msg_id":"-","newrelic.logs.batchIndex":3,"newrelic.source":"api.logs","plugin.type":"ktranslate-syslog","priority":14,"proc_id":"1588","severity":6,"structured_data":"-","tags.container_service":"syslog","timestamp":1761252649725,"version":1},{"app_name":"Light.Monitor.Wrapper","client":"172.17.0.1:46860","collector.name":"ktranslate","device_name":"HubitatC8Pro-2","facility":1,"hostname":"HubitatC8Pro-2","instrumentation.name":"ktranslate-syslog","instrumentation.provider":"kentik","message":"Light Monitor App: Waiting 60 seconds after refresh before checking state for Kitchen Sink Lights","messageId":"a5f140c5-da87-4f92-9c07-1e44eead6c4f","msg_id":"-","newrelic.logs.batchIndex":4,"newrelic.source":"api.logs","plugin.type":"ktranslate-syslog","priority":15,"proc_id":"1588","severity":7,"structured_data":"-","tags.container_service":"syslog","timestamp":1761252649733,"version":1},{"app_name":"Kitchen.Sink.Lights","client":"172.17.0.1:46860","collector.name":"ktranslate","device_name":"HubitatC8Pro-2","facility":1,"hostname":"HubitatC8Pro-2","instrumentation.name":"ktranslate-syslog","instrumentation.provider":"kentik","message":"Kitchen Sink Lights is on [digital]","messageId":"6d88e31b-04e8-4cfe-962d-7ae96f835246","msg_id":"-","newrelic.logs.batchIndex":1,"newrelic.source":"api.logs","plugin.type":"ktranslate-syslog","priority":14,"proc_id":"2997","severity":6,"structured_data":"-","tags.container_service":"syslog","timestamp":1761252650297,"version":1},{"app_name":"Kitchen.Sink.Lights","client":"172.17.0.1:46860","collector.name":"ktranslate","device_name":"HubitatC8Pro-2","facility":1,"hostname":"HubitatC8Pro-2","instrumentation.name":"ktranslate-syslog","instrumentation.provider":"kentik","message":"Kitchen Sink Lights is at 99% [digital]","messageId":"d10657c3-55be-47da-af1f-4de45108fda9","msg_id":"-","newrelic.logs.batchIndex":2,"newrelic.source":"api.logs","plugin.type":"ktranslate-syslog","priority":14,"proc_id":"2997","severity":6,"structured_data":"-","tags.container_service":"syslog","timestamp":1761252650299,"version":1},{"app_name":"Light.Monitor.Wrapper","client":"172.17.0.1:46860","collector.name":"ktranslate","device_name":"HubitatC8Pro-2","facility":1,"hostname":"HubitatC8Pro-2","instrumentation.name":"ktranslate-syslog","instrumentation.provider":"kentik","message":"Light Monitor App: Devices currently in monitoringState: Front Door Light (ID: 1920), Kitchen Sink Lights (ID: 2997), Pool Light (ID: 1870), Garage Inside Light (ID: 855), Kitchen Desk Light (ID: 977), Kitchen Counter Light Right (ID: 956), Patio Lights (ID: 968), Kitchen Counter Light Left (ID: 957), Patio Door and Back Deck Steps Lights (ID: 969), Garage Side Outside Light (ID: 1380)","messageId":"d9b41140-63ed-4607-991f-2bd927529311","msg_id":"-","newrelic.logs.batchIndex":5,"newrelic.source":"api.logs","plugin.type":"ktranslate-syslog","priority":15,"proc_id":"1588","severity":7,"structured_data":"-","tags.container_service":"syslog","timestamp":1761252708817,"version":1},{"app_name":"Light.Monitor.Wrapper","client":"172.17.0.1:46860","collector.name":"ktranslate","device_name":"HubitatC8Pro-2","facility":1,"hostname":"HubitatC8Pro-2","instrumentation.name":"ktranslate-syslog","instrumentation.provider":"kentik","message":"Light Monitor App: Devices currently in monitoringState: Front Door Light (ID: 1920), Kitchen Sink Lights (ID: 2997), Pool Light (ID: 1870), Garage Inside Light (ID: 855), Kitchen Desk Light (ID: 977), Kitchen Counter Light Right (ID: 956), Patio Lights (ID: 968), Kitchen Counter Light Left (ID: 957), Patio Door and Back Deck Steps Lights (ID: 969), Garage Side Outside Light (ID: 1380)","messageId":"00a85f97-66be-44f6-ab08-5e8fb2a246b0","msg_id":"-","newrelic.logs.batchIndex":2,"newrelic.source":"api.logs","plugin.type":"ktranslate-syslog","priority":15,"proc_id":"1588","severity":7,"structured_data":"-","tags.container_service":"syslog","timestamp":1761252709063,"version":1},{"app_name":"Kitchen.Sink.Lights","client":"172.17.0.1:46860","collector.name":"ktranslate","device_name":"HubitatC8Pro","facility":1,"hostname":"HubitatC8Pro","instrumentation.name":"ktranslate-syslog","instrumentation.provider":"kentik","message":"Kitchen Sink Lights on HubitatC8Pro-2 was turned off [digital]","messageId":"a0548325-c3f7-4587-a0f3-943a29890619","msg_id":"-","newrelic.logs.batchIndex":10,"newrelic.source":"api.logs","plugin.type":"ktranslate-syslog","priority":14,"proc_id":"4390","severity":6,"structured_data":"-","tags.container_service":"syslog","timestamp":1761252709542,"version":1},{"app_name":"Light.Monitor.Wrapper","client":"172.17.0.1:46860","collector.name":"ktranslate","device_name":"HubitatC8Pro-2","facility":1,"hostname":"HubitatC8Pro-2","instrumentation.name":"ktranslate-syslog","instrumentation.provider":"kentik","message":"Light Monitor App: Checking device Kitchen Sink Lights after refresh - Current state: on, Desired state: off, Elapsed time: 3572.007s","messageId":"d88a5b0c-4e95-48fe-92eb-b952ad8f4c80","msg_id":"-","newrelic.logs.batchIndex":19,"newrelic.source":"api.logs","plugin.type":"ktranslate-syslog","priority":15,"proc_id":"1588","severity":7,"structured_data":"-","tags.container_service":"syslog","timestamp":1761252709752,"version":1},{"app_name":"Light.Monitor.Wrapper","client":"172.17.0.1:46860","collector.name":"ktranslate","device_name":"HubitatC8Pro-2","facility":1,"hostname":"HubitatC8Pro-2","instrumentation.name":"ktranslate-syslog","instrumentation.provider":"kentik","message":"Light Monitor App: REFRESH SUCCESS - Light Kitchen Sink Lights reports on (expected off) - refresh command worked, proceeding to correct","messageId":"a02d2976-e69a-46b7-a716-6f5a2bcb5de8","msg_id":"-","newrelic.logs.batchIndex":20,"newrelic.source":"api.logs","plugin.type":"ktranslate-syslog","priority":14,"proc_id":"1588","severity":6,"structured_data":"-","tags.container_service":"syslog","timestamp":1761252709754,"version":1},{"app_name":"Light.Monitor.Wrapper","client":"172.17.0.1:46860","collector.name":"ktranslate","device_name":"HubitatC8Pro-2","facility":1,"hostname":"HubitatC8Pro-2","instrumentation.name":"ktranslate-syslog","instrumentation.provider":"kentik","message":"Light Monitor App: Light Kitchen Sink Lights not in desired state (off). Current state: on. Retry attempt 1 (refresh confirmed working)","messageId":"11773471-d920-4603-9c13-cffa26d70d18","msg_id":"-","newrelic.logs.batchIndex":22,"newrelic.source":"api.logs","plugin.type":"ktranslate-syslog","priority":14,"proc_id":"1588","severity":6,"structured_data":"-","tags.container_service":"syslog","timestamp":1761252709757,"version":1},{"app_name":"Light.Monitor.Wrapper","client":"172.17.0.1:46860","collector.name":"ktranslate","device_name":"HubitatC8Pro-2","facility":1,"hostname":"HubitatC8Pro-2","instrumentation.name":"ktranslate-syslog","instrumentation.provider":"kentik","message":"Light Monitor App: Sending OFF command to device Kitchen Sink Lights","messageId":"a6630b53-bc19-49eb-af2e-646995be3240","msg_id":"-","newrelic.logs.batchIndex":23,"newrelic.source":"api.logs","plugin.type":"ktranslate-syslog","priority":15,"proc_id":"1588","severity":7,"structured_data":"-","tags.container_service":"syslog","timestamp":1761252709758,"version":1},{"app_name":"Light.Monitor.Wrapper","client":"172.17.0.1:46860","collector.name":"ktranslate","device_name":"HubitatC8Pro-2","facility":1,"hostname":"HubitatC8Pro-2","instrumentation.name":"ktranslate-syslog","instrumentation.provider":"kentik","message":"Light Monitor App: Updated last command time for device Kitchen Sink Lights","messageId":"ef6168d4-dc0a-497c-81d8-16f7beb60ac7","msg_id":"-","newrelic.logs.batchIndex":24,"newrelic.source":"api.logs","plugin.type":"ktranslate-syslog","priority":15,"proc_id":"1588","severity":7,"structured_data":"-","tags.container_service":"syslog","timestamp":1761252709763,"version":1},{"app_name":"Light.Monitor.Wrapper","client":"172.17.0.1:46860","collector.name":"ktranslate","device_name":"HubitatC8Pro-2","facility":1,"hostname":"HubitatC8Pro-2","instrumentation.name":"ktranslate-syslog","instrumentation.provider":"kentik","message":"Light Monitor App: Scheduling next refresh and check for device Kitchen Sink Lights in 30 seconds","messageId":"7af6ba15-4faa-4132-8d57-274fd48b85ef","msg_id":"-","newrelic.logs.batchIndex":25,"newrelic.source":"api.logs","plugin.type":"ktranslate-syslog","priority":15,"proc_id":"1588","severity":7,"structured_data":"-","tags.container_service":"syslog","timestamp":1761252709764,"version":1},{"app_name":"Kitchen.Sink.Lights","client":"172.17.0.1:46860","collector.name":"ktranslate","device_name":"HubitatC8Pro-2","facility":1,"hostname":"HubitatC8Pro-2","instrumentation.name":"ktranslate-syslog","instrumentation.provider":"kentik","message":"Kitchen Sink Lights was turned off [digital]","messageId":"890deec3-78d9-483d-ad93-1f5108612bdb","msg_id":"-","newrelic.logs.batchIndex":1,"newrelic.source":"api.logs","plugin.type":"ktranslate-syslog","priority":14,"proc_id":"2997","severity":6,"structured_data":"-","tags.container_service":"syslog","timestamp":1761252710317,"version":1},{"app_name":"Light.Monitor.Wrapper","client":"172.17.0.1:46860","collector.name":"ktranslate","device_name":"HubitatC8Pro-2","facility":1,"hostname":"HubitatC8Pro-2","instrumentation.name":"ktranslate-syslog","instrumentation.provider":"kentik","message":"Light Monitor App: Devices currently in monitoringState: Front Door Light (ID: 1920), Kitchen Sink Lights (ID: 2997), Garage Inside Light Between Doors (ID: 893), Pool Light (ID: 1870), Garage Inside Light (ID: 855), Kitchen Desk Light (ID: 977), Kitchen Counter Light Right (ID: 956), Patio Lights (ID: 968), Kitchen Counter Light Left (ID: 957), Patio Door and Back Deck Steps Lights (ID: 969), Garage Side Outside Light (ID: 1380)","messageId":"d296eac5-db2c-4391-b1fa-165ded35348e","msg_id":"-","newrelic.logs.batchIndex":2,"newrelic.source":"api.logs","plugin.type":"ktranslate-syslog","priority":15,"proc_id":"1588","severity":7,"structured_data":"-","tags.container_service":"syslog","timestamp":1761252710335,"version":1},{"app_name":"Light.Monitor.Wrapper","client":"172.17.0.1:46860","collector.name":"ktranslate","device_name":"HubitatC8Pro-2","facility":1,"hostname":"HubitatC8Pro-2","instrumentation.name":"ktranslate-syslog","instrumentation.provider":"kentik","message":"Light Monitor App: Checking for stuck monitoring state for Kitchen Sink Lights:","messageId":"5332d1d3-2254-4773-9270-3d1c353c1635","msg_id":"-","newrelic.logs.batchIndex":3,"newrelic.source":"api.logs","plugin.type":"ktranslate-syslog","priority":15,"proc_id":"1588","severity":7,"structured_data":"-","tags.container_service":"syslog","timestamp":1761252710336,"version":1},{"app_name":"Light.Monitor.Wrapper","client":"172.17.0.1:46860","collector.name":"ktranslate","device_name":"HubitatC8Pro-2","facility":1,"hostname":"HubitatC8Pro-2","instrumentation.name":"ktranslate-syslog","instrumentation.provider":"kentik","message":"Light Monitor App:   - Desired state: off, Current monitoring state: [desiredState:off, lastCheck:1761249109752, initialState:off, refreshCount:1, lastCommand:off, externalEvent:true, checkCount:1, startTime:1761245537744, deviceName:Kitchen Sink Lights, waitingForRefresh:false, refreshSent:true]","messageId":"70acf037-8fcb-4143-bd80-b010d69ca45b","msg_id":"-","newrelic.logs.batchIndex":7,"newrelic.source":"api.logs","plugin.type":"ktranslate-syslog","priority":15,"proc_id":"1588","severity":7,"structured_data":"-","tags.container_service":"syslog","timestamp":1761252710341,"version":1},{"app_name":"Light.Monitor.Wrapper","client":"172.17.0.1:46860","collector.name":"ktranslate","device_name":"HubitatC8Pro-2","facility":1,"hostname":"HubitatC8Pro-2","instrumentation.name":"ktranslate-syslog","instrumentation.provider":"kentik","message":"Light Monitor App: Device Kitchen Sink Lights (ID: 2997) is actively being monitored - ignoring new event due to cooldown","messageId":"e4972fce-eaec-4a02-8ebe-572d0664932d","msg_id":"-","newrelic.logs.batchIndex":9,"newrelic.source":"api.logs","plugin.type":"ktranslate-syslog","priority":15,"proc_id":"1588","severity":7,"structured_data":"-","tags.container_service":"syslog","timestamp":1761252710344,"version":1},{"app_name":"Kitchen.Sink.Lights","client":"172.17.0.1:46860","collector.name":"ktranslate","device_name":"HubitatC8Pro","facility":1,"hostname":"HubitatC8Pro","instrumentation.name":"ktranslate-syslog","instrumentation.provider":"kentik","message":"Kitchen Sink Lights on HubitatC8Pro-2 is off [digital]","messageId":"052ebd85-8b68-46c9-ba56-d938cb500142","msg_id":"-","newrelic.logs.batchIndex":2,"newrelic.source":"api.logs","plugin.type":"ktranslate-syslog","priority":14,"proc_id":"4390","severity":6,"structured_data":"-","tags.container_service":"syslog","timestamp":1761252739434,"version":1},{"app_name":"Light.Monitor.Wrapper","client":"172.17.0.1:46860","collector.name":"ktranslate","device_name":"HubitatC8Pro-2","facility":1,"hostname":"HubitatC8Pro-2","instrumentation.name":"ktranslate-syslog","instrumentation.provider":"kentik","message":"Light Monitor App: Sending REFRESH command to device Kitchen Sink Lights to get accurate state","messageId":"cb6ffc7f-7e0d-4399-8d40-7a838d349e45","msg_id":"-","newrelic.logs.batchIndex":4,"newrelic.source":"api.logs","plugin.type":"ktranslate-syslog","priority":14,"proc_id":"1588","severity":6,"structured_data":"-","tags.container_service":"syslog","timestamp":1761252739819,"version":1},{"app_name":"Light.Monitor.Wrapper","client":"172.17.0.1:46860","collector.name":"ktranslate","device_name":"HubitatC8Pro-2","facility":1,"hostname":"HubitatC8Pro-2","instrumentation.name":"ktranslate-syslog","instrumentation.provider":"kentik","message":"Light Monitor App: Waiting 60 seconds after refresh before checking state for Kitchen Sink Lights","messageId":"247b99e1-f792-4df2-be05-65a282473f1f","msg_id":"-","newrelic.logs.batchIndex":5,"newrelic.source":"api.logs","plugin.type":"ktranslate-syslog","priority":15,"proc_id":"1588","severity":7,"structured_data":"-","tags.container_service":"syslog","timestamp":1761252739825,"version":1},{"app_name":"Kitchen.Sink.Lights","client":"172.17.0.1:46860","collector.name":"ktranslate","device_name":"HubitatC8Pro-2","facility":1,"hostname":"HubitatC8Pro-2","instrumentation.name":"ktranslate-syslog","instrumentation.provider":"kentik","message":"Kitchen Sink Lights is off [digital]","messageId":"e9863be2-5a07-4957-8e2c-24170a5f64db","msg_id":"-","newrelic.logs.batchIndex":1,"newrelic.source":"api.logs","plugin.type":"ktranslate-syslog","priority":14,"proc_id":"2997","severity":6,"structured_data":"-","tags.container_service":"syslog","timestamp":1761252740383,"version":1},{"app_name":"Light.Monitor.Wrapper","client":"172.17.0.1:46860","collector.name":"ktranslate","device_name":"HubitatC8Pro-2","facility":1,"hostname":"HubitatC8Pro-2","instrumentation.name":"ktranslate-syslog","instrumentation.provider":"kentik","message":"Light Monitor App: Checking device Kitchen Sink Lights after refresh - Current state: off, Desired state: off, Elapsed time: 3662.116s","messageId":"d02f2939-4f52-45a7-a73d-609042fba6f6","msg_id":"-","newrelic.logs.batchIndex":146,"newrelic.source":"api.logs","plugin.type":"ktranslate-syslog","priority":15,"proc_id":"1588","severity":7,"structured_data":"-","tags.container_service":"syslog","timestamp":1761252799861,"version":1},{"app_name":"Light.Monitor.Wrapper","client":"172.17.0.1:46860","collector.name":"ktranslate","device_name":"HubitatC8Pro-2","facility":1,"hostname":"HubitatC8Pro-2","instrumentation.name":"ktranslate-syslog","instrumentation.provider":"kentik","message":"Light Monitor App: MONITORING COMPLETED - Light Kitchen Sink Lights successfully changed to off after 3662 seconds and 1 commands (verified through refresh)","messageId":"ee1210a0-6d6a-4342-b09b-059e20b50373","msg_id":"-","newrelic.logs.batchIndex":151,"newrelic.source":"api.logs","plugin.type":"ktranslate-syslog","priority":14,"proc_id":"1588","severity":6,"structured_data":"-","tags.container_service":"syslog","timestamp":1761252799863,"version":1},{"app_name":"Light.Monitor.Wrapper","client":"172.17.0.1:46860","collector.name":"ktranslate","device_name":"HubitatC8Pro-2","facility":1,"hostname":"HubitatC8Pro-2","instrumentation.name":"ktranslate-syslog","instrumentation.provider":"kentik","message":"Light Monitor App: Removing monitoring state for device Kitchen Sink Lights","messageId":"dee87e99-d242-4b4c-9ca9-67c692506ab6","msg_id":"-","newrelic.logs.batchIndex":152,"newrelic.source":"api.logs","plugin.type":"ktranslate-syslog","priority":15,"proc_id":"1588","severity":7,"structured_data":"-","tags.container_service":"syslog","timestamp":1761252799865,"version":1}]